{
  "query_details": {
    "title": "pandemic",
    "date_resolution": "day"
  },
  "timeline": [
    {
      "series": "Volume Intensity",
      "data": [
        {
          "date": "20250819T000000Z",
          "value": 1.2914
        },
        {
          "date": "20250820T000000Z",
          "value": 1.2273
        },
        {
          "date": "20250821T000000Z",
          "value": 1.2888
        },
        {
          "date": "20250822T000000Z",
          "value": 1.1316
        },
        {
          "date": "20250823T000000Z",
          "value": 0.8868
        },
        {
          "date": "20250824T000000Z",
          "value": 1.0164
        },
        {
          "date": "20250825T000000Z",
          "value": 1.157
        },
        {
          "date": "20250826T000000Z",
          "value": 1.0244
        },
        {
          "date": "20250827T000000Z",
          "value": 1.2192
        },
        {
          "date": "20250828T000000Z",
          "value": 1.1477
        },
        {
          "date": "20250829T000000Z",
          "value": 1.2531
        },
        {
          "date": "20250830T000000Z",
          "value": 0.9765
        },
        {
          "date": "20250831T000000Z",
          "value": 1.4241
        },
        {
          "date": "20250901T000000Z",
          "value": 0.9465
        },
        {
          "date": "20250902T000000Z",
          "value": 1.0747
        },
        {
          "date": "20250903T000000Z",
          "value": 1.1724
        },
        {
          "date": "20250904T000000Z",
          "value": 1.3637
        },
        {
          "date": "20250905T000000Z",
          "value": 1.3212
        },
        {
          "date": "20250906T000000Z",
          "value": 1.1756
        },
        {
          "date": "20250907T000000Z",
          "value": 0.9065
        },
        {
          "date": "20250908T000000Z",
          "value": 1.0046
        },
        {
          "date": "20250909T000000Z",
          "value": 1.1417
        },
        {
          "date": "20250910T000000Z",
          "value": 1.0198
        },
        {
          "date": "20250911T000000Z",
          "value": 1.1824
        },
        {
          "date": "20250912T000000Z",
          "value": 1.0274
        },
        {
          "date": "20250913T000000Z",
          "value": 0.9291
        },
        {
          "date": "20250914T000000Z",
          "value": 0.9357
        },
        {
          "date": "20250915T000000Z",
          "value": 1.1246
        },
        {
          "date": "20250916T000000Z",
          "value": 1.2376
        },
        {
          "date": "20250917T000000Z",
          "value": 0.9995
        },
        {
          "date": "20250918T000000Z",
          "value": 1.0428
        },
        {
          "date": "20250919T000000Z",
          "value": 1.0495
        },
        {
          "date": "20250920T000000Z",
          "value": 0.9381
        },
        {
          "date": "20250921T000000Z",
          "value": 0.8977
        },
        {
          "date": "20250922T000000Z",
          "value": 1.015
        },
        {
          "date": "20250923T000000Z",
          "value": 1.0688
        },
        {
          "date": "20250924T000000Z",
          "value": 1.1198
        },
        {
          "date": "20250925T000000Z",
          "value": 1.2546
        },
        {
          "date": "20250926T000000Z",
          "value": 0.9465
        },
        {
          "date": "20250927T000000Z",
          "value": 1.0311
        },
        {
          "date": "20250928T000000Z",
          "value": 1.0466
        },
        {
          "date": "20250929T000000Z",
          "value": 1.0498
        },
        {
          "date": "20250930T000000Z",
          "value": 1.0946
        },
        {
          "date": "20251001T000000Z",
          "value": 1.2302
        },
        {
          "date": "20251002T000000Z",
          "value": 1.0903
        },
        {
          "date": "20251003T000000Z",
          "value": 1.1229
        },
        {
          "date": "20251004T000000Z",
          "value": 0.8944
        },
        {
          "date": "20251005T000000Z",
          "value": 0.8526
        },
        {
          "date": "20251006T000000Z",
          "value": 1.0857
        },
        {
          "date": "20251007T000000Z",
          "value": 0.9859
        },
        {
          "date": "20251008T000000Z",
          "value": 1.0854
        },
        {
          "date": "20251009T000000Z",
          "value": 0.9802
        },
        {
          "date": "20251010T000000Z",
          "value": 1.0304
        },
        {
          "date": "20251011T000000Z",
          "value": 1.0566
        },
        {
          "date": "20251012T000000Z",
          "value": 0.9999
        },
        {
          "date": "20251013T000000Z",
          "value": 0.9041
        },
        {
          "date": "20251014T000000Z",
          "value": 1.0184
        },
        {
          "date": "20251015T000000Z",
          "value": 1.0503
        },
        {
          "date": "20251016T000000Z",
          "value": 1.2455
        },
        {
          "date": "20251017T000000Z",
          "value": 0.9037
        },
        {
          "date": "20251018T000000Z",
          "value": 0.8725
        },
        {
          "date": "20251019T000000Z",
          "value": 0.9679
        },
        {
          "date": "20251020T000000Z",
          "value": 0.8919
        },
        {
          "date": "20251021T000000Z",
          "value": 1.0178
        },
        {
          "date": "20251022T000000Z",
          "value": 1.1812
        },
        {
          "date": "20251023T000000Z",
          "value": 1.2726
        },
        {
          "date": "20251024T000000Z",
          "value": 1.1423
        },
        {
          "date": "20251025T000000Z",
          "value": 0.9126
        },
        {
          "date": "20251026T000000Z",
          "value": 0.9177
        },
        {
          "date": "20251027T000000Z",
          "value": 1.0525
        },
        {
          "date": "20251028T000000Z",
          "value": 1.2519
        },
        {
          "date": "20251029T000000Z",
          "value": 1.1198
        },
        {
          "date": "20251030T000000Z",
          "value": 1.0848
        },
        {
          "date": "20251031T000000Z",
          "value": 1.0347
        },
        {
          "date": "20251101T000000Z",
          "value": 1.072
        },
        {
          "date": "20251102T000000Z",
          "value": 0.9136
        },
        {
          "date": "20251103T000000Z",
          "value": 1.0732
        },
        {
          "date": "20251104T000000Z",
          "value": 1.128
        },
        {
          "date": "20251105T000000Z",
          "value": 1.1229
        },
        {
          "date": "20251106T000000Z",
          "value": 1.1257
        },
        {
          "date": "20251107T000000Z",
          "value": 1.0096
        },
        {
          "date": "20251108T000000Z",
          "value": 0.8168
        },
        {
          "date": "20251109T000000Z",
          "value": 0.8218
        },
        {
          "date": "20251110T000000Z",
          "value": 0.9383
        },
        {
          "date": "20251111T000000Z",
          "value": 1.0402
        },
        {
          "date": "20251112T000000Z",
          "value": 1.0854
        },
        {
          "date": "20251113T000000Z",
          "value": 1.2259
        },
        {
          "date": "20251114T000000Z",
          "value": 0.9931
        },
        {
          "date": "20251115T000000Z",
          "value": 0.9993
        },
        {
          "date": "20251116T000000Z",
          "value": 1.0161
        },
        {
          "date": "20251117T000000Z",
          "value": 0.9543
        },
        {
          "date": "20251118T000000Z",
          "value": 0.9548
        },
        {
          "date": "20251119T000000Z",
          "value": 0.9994
        },
        {
          "date": "20251120T000000Z",
          "value": 1.3109
        },
        {
          "date": "20251121T000000Z",
          "value": 1.2456
        },
        {
          "date": "20251122T000000Z",
          "value": 1.0523
        },
        {
          "date": "20251123T000000Z",
          "value": 0.922
        },
        {
          "date": "20251124T000000Z",
          "value": 0.9953
        },
        {
          "date": "20251125T000000Z",
          "value": 1.0959
        },
        {
          "date": "20251126T000000Z",
          "value": 1.173
        },
        {
          "date": "20251127T000000Z",
          "value": 1.027
        },
        {
          "date": "20251128T000000Z",
          "value": 1.0671
        },
        {
          "date": "20251129T000000Z",
          "value": 1.0171
        },
        {
          "date": "20251130T000000Z",
          "value": 0.9897
        },
        {
          "date": "20251201T000000Z",
          "value": 1.0558
        },
        {
          "date": "20251202T000000Z",
          "value": 1.1095
        },
        {
          "date": "20251203T000000Z",
          "value": 1.0628
        },
        {
          "date": "20251204T000000Z",
          "value": 1.002
        },
        {
          "date": "20251205T000000Z",
          "value": 0.9465
        },
        {
          "date": "20251206T000000Z",
          "value": 0.4049
        },
        {
          "date": "20251207T000000Z",
          "value": 0.9458
        },
        {
          "date": "20251208T000000Z",
          "value": 1.0278
        },
        {
          "date": "20251209T000000Z",
          "value": 1.0694
        },
        {
          "date": "20251210T000000Z",
          "value": 1.1017
        },
        {
          "date": "20251211T000000Z",
          "value": 1.0911
        },
        {
          "date": "20251212T000000Z",
          "value": 1.1078
        },
        {
          "date": "20251213T000000Z",
          "value": 1.0133
        },
        {
          "date": "20251214T000000Z",
          "value": 0.8919
        },
        {
          "date": "20251215T000000Z",
          "value": 1.0183
        },
        {
          "date": "20251216T000000Z",
          "value": 1.1113
        },
        {
          "date": "20251217T000000Z",
          "value": 1.1252
        },
        {
          "date": "20251218T000000Z",
          "value": 1.2769
        },
        {
          "date": "20251219T000000Z",
          "value": 0.9516
        },
        {
          "date": "20251220T000000Z",
          "value": 0.9379
        },
        {
          "date": "20251221T000000Z",
          "value": 0.8254
        },
        {
          "date": "20251222T000000Z",
          "value": 0.7795
        },
        {
          "date": "20251223T000000Z",
          "value": 0.952
        },
        {
          "date": "20251224T000000Z",
          "value": 0.9688
        },
        {
          "date": "20251225T000000Z",
          "value": 0.6824
        },
        {
          "date": "20251226T000000Z",
          "value": 0.9305
        },
        {
          "date": "20251227T000000Z",
          "value": 0.7953
        },
        {
          "date": "20251228T000000Z",
          "value": 0.9017
        },
        {
          "date": "20251229T000000Z",
          "value": 0.932
        },
        {
          "date": "20251230T000000Z",
          "value": 0.9753
        },
        {
          "date": "20251231T000000Z",
          "value": 1.4322
        },
        {
          "date": "20260101T000000Z",
          "value": 1.1922
        },
        {
          "date": "20260102T000000Z",
          "value": 1.1463
        },
        {
          "date": "20260103T000000Z",
          "value": 0.7346
        },
        {
          "date": "20260104T000000Z",
          "value": 0.8022
        },
        {
          "date": "20260105T000000Z",
          "value": 0.9285
        },
        {
          "date": "20260106T000000Z",
          "value": 1.0811
        },
        {
          "date": "20260107T000000Z",
          "value": 1.1213
        },
        {
          "date": "20260108T000000Z",
          "value": 1.0532
        },
        {
          "date": "20260109T000000Z",
          "value": 1.0874
        },
        {
          "date": "20260110T000000Z",
          "value": 0.9289
        },
        {
          "date": "20260111T000000Z",
          "value": 0.8675
        },
        {
          "date": "20260112T000000Z",
          "value": 0.8684
        },
        {
          "date": "20260113T000000Z",
          "value": 1.0125
        },
        {
          "date": "20260114T000000Z",
          "value": 0.9847
        },
        {
          "date": "20260115T000000Z",
          "value": 0.9992
        },
        {
          "date": "20260116T000000Z",
          "value": 0.8715
        },
        {
          "date": "20260117T000000Z",
          "value": 0.8111
        },
        {
          "date": "20260118T000000Z",
          "value": 0.8709
        },
        {
          "date": "20260119T000000Z",
          "value": 0.7756
        },
        {
          "date": "20260120T000000Z",
          "value": 1.0483
        },
        {
          "date": "20260121T000000Z",
          "value": 0.9017
        },
        {
          "date": "20260122T000000Z",
          "value": 0.8993
        },
        {
          "date": "20260123T000000Z",
          "value": 1.0873
        },
        {
          "date": "20260124T000000Z",
          "value": 0.714
        },
        {
          "date": "20260125T000000Z",
          "value": 1.058
        },
        {
          "date": "20260126T000000Z",
          "value": 1.0548
        },
        {
          "date": "20260127T000000Z",
          "value": 1.3586
        },
        {
          "date": "20260128T000000Z",
          "value": 1.2026
        },
        {
          "date": "20260129T000000Z",
          "value": 1.0718
        },
        {
          "date": "20260130T000000Z",
          "value": 0.9655
        },
        {
          "date": "20260131T000000Z",
          "value": 0.883
        },
        {
          "date": "20260201T000000Z",
          "value": 0.8377
        },
        {
          "date": "20260202T000000Z",
          "value": 0.8972
        },
        {
          "date": "20260203T000000Z",
          "value": 1.0973
        },
        {
          "date": "20260204T000000Z",
          "value": 0.9507
        },
        {
          "date": "20260205T000000Z",
          "value": 1.1354
        },
        {
          "date": "20260206T000000Z",
          "value": 0.9915
        },
        {
          "date": "20260207T000000Z",
          "value": 1.0445
        },
        {
          "date": "20260208T000000Z",
          "value": 0.8957
        },
        {
          "date": "20260209T000000Z",
          "value": 0.8317
        },
        {
          "date": "20260210T000000Z",
          "value": 0.8371
        },
        {
          "date": "20260211T000000Z",
          "value": 1.0023
        },
        {
          "date": "20260212T000000Z",
          "value": 1.0549
        },
        {
          "date": "20260213T000000Z",
          "value": 0.8489
        },
        {
          "date": "20260214T000000Z",
          "value": 0.9874
        }
      ]
    }
  ]
}